{
  "fuente": "Web Service",
  "empresa": "EDESUR",
  "totalUsuariosSinSuministro": "3.414",
  "totalUsuariosConSuministro": "2.530.171",
  "ultimaActualizacion": "18:15",
  "totalUsuariosAyer": "34.220",
  "cortesPreventivos": [],
  "cortesProgramados": [
    {
      "partido": "CAPITAL FEDERAL",
      "localidad": "VILLA CRESPO",
      "subestacion_alimentador": "143-SANTA RITA / R:143-3-36 / 143-3-36",
      "usuarios": "619",
      "normalizacion": "2022-05-04 21:00"
    },
    {
      "partido": "LOMAS DE ZAMORA",
      "localidad": "LOMAS DE ZAMORA",
      "subestacion_alimentador": "84-TEMPERLEY / R:084-1-18 / 084-1-18",
      "usuarios": "481",
      "normalizacion": "Sin datos"
    }
  ],
  "cortesServicioMedia": [
    {
      "partido": "ALMIRANTE BROWN",
      "localidad": "RAFAEL CALZADA",
      "subestacion_alimentador": "184-MONTE CHINGOLO / R:184-3-32 / 184-3-32",
      "usuarios": "229",
      "normalizacion": "2022-05-04 21:48"
    },
    {
      "partido": "ALMIRANTE BROWN",
      "localidad": "SAN JOSE",
      "subestacion_alimentador": "184-MONTE CHINGOLO / R:184-3-32 / 184-3-32",
      "usuarios": "1435",
      "normalizacion": "2022-05-04 21:48"
    },
    {
      "partido": "QUILMES",
      "localidad": "SAN FRANCISCO SOLANO (Q)",
      "subestacion_alimentador": "184-MONTE CHINGOLO / R:184-3-32 / 184-3-32",
      "usuarios": "244",
      "normalizacion": "2022-05-04 21:48"
    }
  ],
  "cortesComunicados": [],
  "cortesServicioBaja": [
    {
      "partido": "ALMIRANTE BROWN",
      "localidad": "LONGCHAMPS",
      "usuarios": "11"
    },
    {
      "partido": "CAPITAL",
      "localidad": "CABALLITO",
      "usuarios": "75"
    },
    {
      "partido": "CAPITAL",
      "localidad": "CAPITAL",
      "usuarios": "15"
    },
    {
      "partido": "CAPITAL",
      "localidad": "LINIERS",
      "usuarios": "12"
    },
    {
      "partido": "CAPITAL",
      "localidad": "PARQUE PATRICIOS",
      "usuarios": "56"
    },
    {
      "partido": "CAPITAL",
      "localidad": "VILLA SOLDATI",
      "usuarios": "16"
    },
    {
      "partido": "ESTEBAN ECHEVERRIA",
      "localidad": "LUIS GUILLON",
      "usuarios": "74"
    },
    {
      "partido": "EZEIZA",
      "localidad": "JOSE MARIA EZEIZA",
      "usuarios": "39"
    },
    {
      "partido": "LANUS",
      "localidad": "LANUS",
      "usuarios": "54"
    },
    {
      "partido": "LOMAS DE ZAMORA",
      "localidad": "TEMPERLEY",
      "usuarios": "18"
    },
    {
      "partido": "QUILMES",
      "localidad": "BERNAL",
      "usuarios": "29"
    },
    {
      "partido": "QUILMES",
      "localidad": "SAN FRANCISCO SOLANO (Q)",
      "usuarios": "7"
    }
  ]
}
