{
  "fuente": "Web Service",
  "empresa": "EDESUR",
  "totalUsuariosSinSuministro": "6.366",
  "totalUsuariosConSuministro": "2.527.814",
  "ultimaActualizacion": "17:15",
  "totalUsuariosAyer": "31.870",
  "cortesPreventivos": [],
  "cortesProgramados": [
    {
      "partido": "CAPITAL FEDERAL",
      "localidad": "BALVANERA GP",
      "subestacion_alimentador": "113-ONCE / R:113-4-45 / 113-4-45",
      "usuarios": "346",
      "normalizacion": "Sin datos"
    },
    {
      "partido": "CAPITAL FEDERAL",
      "localidad": "MATADEROS",
      "subestacion_alimentador": "48-PERITO MORENO / R:048-1-11 / 048-1-11",
      "usuarios": "509",
      "normalizacion": "2022-04-05 19:25"
    },
    {
      "partido": "EZEIZA",
      "localidad": "CARLOS SPEGAZZINNI",
      "subestacion_alimentador": "270-SPEGAZZINI / R:270-1-13 / 270-1-13",
      "usuarios": "232",
      "normalizacion": "Sin datos"
    },
    {
      "partido": "QUILMES",
      "localidad": "EZPELETA",
      "subestacion_alimentador": "175-SOBRAL / R:175-1-13 / 175-1-13",
      "usuarios": "894",
      "normalizacion": "Sin datos"
    },
    {
      "partido": "QUILMES",
      "localidad": "QUILMES OESTE",
      "subestacion_alimentador": "175-SOBRAL / R:175-1-13 / 175-1-13",
      "usuarios": "37",
      "normalizacion": "Sin datos"
    }
  ],
  "cortesServicioMedia": [
    {
      "partido": "FLORENCIO VARELA",
      "localidad": "FLORENCIO VARELA",
      "subestacion_alimentador": "185-BOSQUES / R:185-1-16 / 185-1-16",
      "usuarios": "1735",
      "normalizacion": "Sin datos"
    },
    {
      "partido": "FLORENCIO VARELA",
      "localidad": "ING. ALLAN",
      "subestacion_alimentador": "185-BOSQUES / R:185-1-16 / 185-1-16",
      "usuarios": "2415",
      "normalizacion": "Sin datos"
    }
  ],
  "cortesComunicados": [],
  "cortesServicioBaja": [
    {
      "partido": "CAPITAL",
      "localidad": "BARRACAS",
      "usuarios": "24"
    },
    {
      "partido": "CAPITAL",
      "localidad": "CABALLITO",
      "usuarios": "10"
    },
    {
      "partido": "CAPITAL",
      "localidad": "CAPITAL",
      "usuarios": "21"
    },
    {
      "partido": "CAPITAL",
      "localidad": "MONSERRAT",
      "usuarios": "6"
    },
    {
      "partido": "CAPITAL",
      "localidad": "PARQUE CHACABUCO",
      "usuarios": "6"
    },
    {
      "partido": "CAPITAL",
      "localidad": "PARQUE PATRICIOS",
      "usuarios": "19"
    },
    {
      "partido": "LOMAS DE ZAMORA",
      "localidad": "INGENIERO BUDGE",
      "usuarios": "65"
    },
    {
      "partido": "LOMAS DE ZAMORA",
      "localidad": "VILLA CENTENARIO",
      "usuarios": "18"
    },
    {
      "partido": "QUILMES",
      "localidad": "BERNAL",
      "usuarios": "29"
    }
  ]
}
