{
  "fuente": "Web Service",
  "empresa": "EDESUR",
  "totalUsuariosSinSuministro": "1.817",
  "totalUsuariosConSuministro": "2.531.768",
  "ultimaActualizacion": "13:25",
  "totalUsuariosAyer": "79.726",
  "cortesPreventivos": [],
  "cortesProgramados": [
    {
      "partido": "ESTEBAN ECHEVERRIA",
      "localidad": "9 DE ABRIL",
      "subestacion_alimentador": "281-TRANSRADIO / R:281-3-31 / 281-3-31",
      "usuarios": "494",
      "normalizacion": "Sin datos"
    },
    {
      "partido": "LOMAS DE ZAMORA",
      "localidad": "ZONA RURAL",
      "subestacion_alimentador": "281-TRANSRADIO / R:281-3-31 / 281-3-31",
      "usuarios": "99",
      "normalizacion": "Sin datos"
    }
  ],
  "cortesServicioMedia": [],
  "cortesComunicados": [],
  "cortesServicioBaja": [
    {
      "partido": "ALMIRANTE BROWN",
      "localidad": "ADROGUE",
      "usuarios": "54"
    },
    {
      "partido": "ALMIRANTE BROWN",
      "localidad": "LONGCHAMPS",
      "usuarios": "4"
    },
    {
      "partido": "AVELLANEDA",
      "localidad": "AVELLANEDA",
      "usuarios": "2"
    },
    {
      "partido": "AVELLANEDA",
      "localidad": "PIÑEYRO",
      "usuarios": "2"
    },
    {
      "partido": "AVELLANEDA",
      "localidad": "WILDE",
      "usuarios": "39"
    },
    {
      "partido": "BERAZATEGUI",
      "localidad": "BERAZATEGUI",
      "usuarios": "54"
    },
    {
      "partido": "BERAZATEGUI",
      "localidad": "EL PATO",
      "usuarios": "7"
    },
    {
      "partido": "CAPITAL",
      "localidad": "ALMAGRO",
      "usuarios": "19"
    },
    {
      "partido": "CAPITAL",
      "localidad": "BALVANERA",
      "usuarios": "7"
    },
    {
      "partido": "CAPITAL",
      "localidad": "BOEDO",
      "usuarios": "11"
    },
    {
      "partido": "CAPITAL",
      "localidad": "CABALLITO",
      "usuarios": "34"
    },
    {
      "partido": "CAPITAL",
      "localidad": "CAPITAL",
      "usuarios": "101"
    },
    {
      "partido": "CAPITAL",
      "localidad": "LA BOCA",
      "usuarios": "61"
    },
    {
      "partido": "CAPITAL",
      "localidad": "LINIERS",
      "usuarios": "6"
    },
    {
      "partido": "CAPITAL",
      "localidad": "SAN CRISTOBAL",
      "usuarios": "45"
    },
    {
      "partido": "CAPITAL",
      "localidad": "VILLA DEVOTO",
      "usuarios": "160"
    },
    {
      "partido": "ESTEBAN ECHEVERRIA",
      "localidad": "LUIS GUILLON",
      "usuarios": "31"
    },
    {
      "partido": "ESTEBAN ECHEVERRIA",
      "localidad": "MONTE GRANDE",
      "usuarios": "7"
    },
    {
      "partido": "EZEIZA",
      "localidad": "TRISTAN SUAREZ",
      "usuarios": "6"
    },
    {
      "partido": "FLORENCIO VARELA",
      "localidad": "BOSQUES",
      "usuarios": "35"
    },
    {
      "partido": "FLORENCIO VARELA",
      "localidad": "FLORENCIO VARELA",
      "usuarios": "15"
    },
    {
      "partido": "LANUS",
      "localidad": "MONTE CHINGOLO",
      "usuarios": "16"
    },
    {
      "partido": "LOMAS DE ZAMORA",
      "localidad": "INGENIERO BUDGE",
      "usuarios": "52"
    },
    {
      "partido": "LOMAS DE ZAMORA",
      "localidad": "LOMAS DE ZAMORA",
      "usuarios": "356"
    },
    {
      "partido": "LOMAS DE ZAMORA",
      "localidad": "TEMPERLEY",
      "usuarios": "79"
    },
    {
      "partido": "QUILMES",
      "localidad": "EZPELETA",
      "usuarios": "21"
    }
  ]
}
