{
  "fuente": "Web Service",
  "empresa": "EDESUR",
  "totalUsuariosSinSuministro": "20.601",
  "totalUsuariosConSuministro": "2.512.984",
  "ultimaActualizacion": "19:30",
  "totalUsuariosAyer": "8.460",
  "cortesPreventivos": [],
  "cortesProgramados": [
    {
      "partido": "ALMIRANTE BROWN",
      "localidad": "RAFAEL CALZADA",
      "subestacion_alimentador": "- / R:",
      "usuarios": "1078",
      "normalizacion": "2022-07-13 16:55"
    },
    {
      "partido": "ALMIRANTE BROWN",
      "localidad": "SAN JOSE",
      "subestacion_alimentador": "- / R:",
      "usuarios": "1930",
      "normalizacion": "2022-07-13 16:55"
    },
    {
      "partido": "ESTEBAN ECHEVERRIA",
      "localidad": "EL JAGUEL",
      "subestacion_alimentador": "83-ECHEVERRIA / R:083-3-38 / 083-3-38",
      "usuarios": "201",
      "normalizacion": "2022-07-12 21:14"
    },
    {
      "partido": "LANUS",
      "localidad": "MONTE CHINGOLO",
      "subestacion_alimentador": "184-MONTE CHINGOLO / R:184-2-22 / 184-2-22",
      "usuarios": "2483",
      "normalizacion": "Sin datos"
    },
    {
      "partido": "LOMAS DE ZAMORA",
      "localidad": "LOMAS DE ZAMORA",
      "subestacion_alimentador": "182-SANTA CATALINA / R:182-2-28 / 182-2-28",
      "usuarios": "316",
      "normalizacion": "2022-07-12 23:50"
    },
    {
      "partido": "LOMAS DE ZAMORA",
      "localidad": "TEMPERLEY",
      "subestacion_alimentador": "- / R:",
      "usuarios": "6236",
      "normalizacion": "2022-07-13 16:55"
    },
    {
      "partido": "LOMAS DE ZAMORA",
      "localidad": "ZONA RURAL",
      "subestacion_alimentador": "- / R:",
      "usuarios": "883",
      "normalizacion": "2022-07-13 16:55"
    },
    {
      "partido": "QUILMES",
      "localidad": "BERNAL",
      "subestacion_alimentador": "184-MONTE CHINGOLO / R:184-2-22 / 184-2-22",
      "usuarios": "107",
      "normalizacion": "Sin datos"
    },
    {
      "partido": "QUILMES",
      "localidad": "QUILMES OESTE",
      "subestacion_alimentador": "184-MONTE CHINGOLO / R:184-2-21 / 184-2-21",
      "usuarios": "292",
      "normalizacion": "2022-07-12 22:01"
    },
    {
      "partido": "QUILMES",
      "localidad": "QUILMES OESTE",
      "subestacion_alimentador": "- / R:",
      "usuarios": "1157",
      "normalizacion": "2022-07-13 16:55"
    },
    {
      "partido": "QUILMES",
      "localidad": "SAN FRANCISCO SOLANO (Q)",
      "subestacion_alimentador": "- / R:",
      "usuarios": "705",
      "normalizacion": "2022-07-13 16:55"
    },
    {
      "partido": "QUILMES",
      "localidad": "SAN FRANCISCO SOLANO (Q)",
      "subestacion_alimentador": "184-MONTE CHINGOLO / R:184-2-21 / 184-2-21",
      "usuarios": "438",
      "normalizacion": "2022-07-12 22:01"
    }
  ],
  "cortesServicioMedia": [
    {
      "partido": "ALMIRANTE BROWN",
      "localidad": "RAFAEL CALZADA",
      "subestacion_alimentador": "184-MONTE CHINGOLO / R:184-3-32 / 184-3-32",
      "usuarios": "228",
      "normalizacion": "2022-07-12 22:53"
    },
    {
      "partido": "ALMIRANTE BROWN",
      "localidad": "SAN JOSE",
      "subestacion_alimentador": "184-MONTE CHINGOLO / R:184-3-32 / 184-3-32",
      "usuarios": "1951",
      "normalizacion": "2022-07-12 22:53"
    },
    {
      "partido": "QUILMES",
      "localidad": "SAN FRANCISCO SOLANO (Q)",
      "subestacion_alimentador": "184-MONTE CHINGOLO / R:184-3-32 / 184-3-32",
      "usuarios": "2345",
      "normalizacion": "2022-07-12 22:53"
    }
  ],
  "cortesComunicados": [],
  "cortesServicioBaja": [
    {
      "partido": "ALMIRANTE BROWN",
      "localidad": "ADROGUE",
      "usuarios": "15"
    },
    {
      "partido": "ALMIRANTE BROWN",
      "localidad": "RAFAEL CALZADA",
      "usuarios": "1"
    },
    {
      "partido": "AVELLANEDA",
      "localidad": "AVELLANEDA",
      "usuarios": "23"
    },
    {
      "partido": "BERAZATEGUI",
      "localidad": "BERAZATEGUI",
      "usuarios": "10"
    },
    {
      "partido": "BERAZATEGUI",
      "localidad": "PLATANOS",
      "usuarios": "7"
    },
    {
      "partido": "CAÑUELAS",
      "localidad": "MAXIMO PAZ",
      "usuarios": "12"
    },
    {
      "partido": "CAPITAL",
      "localidad": "BOEDO",
      "usuarios": "41"
    },
    {
      "partido": "CAPITAL",
      "localidad": "LA BOCA",
      "usuarios": "10"
    },
    {
      "partido": "CAPITAL",
      "localidad": "MONSERRAT",
      "usuarios": "19"
    },
    {
      "partido": "CAPITAL",
      "localidad": "NUEVA POMPEYA",
      "usuarios": "7"
    },
    {
      "partido": "FLORENCIO VARELA",
      "localidad": "FLORENCIO VARELA",
      "usuarios": "17"
    },
    {
      "partido": "LANUS",
      "localidad": "REMEDIOS DE ESCALADA",
      "usuarios": "65"
    },
    {
      "partido": "QUILMES",
      "localidad": "QUILMES",
      "usuarios": "24"
    }
  ]
}
