{
  "fuente": "Web Service",
  "empresa": "EDESUR",
  "totalUsuariosSinSuministro": "3.509",
  "totalUsuariosConSuministro": "2.530.671",
  "ultimaActualizacion": "20:05",
  "totalUsuariosAyer": "44.764",
  "cortesPreventivos": [],
  "cortesProgramados": [],
  "cortesServicioMedia": [
    {
      "partido": "CAÑUELAS",
      "localidad": "ZONA RURAL 4",
      "subestacion_alimentador": "271-CAnUELAS / R:271-1-14 / 271-1-14",
      "usuarios": "154",
      "normalizacion": "Sin datos"
    },
    {
      "partido": "CAÑUELAS",
      "localidad": "ZONA RURAL 6",
      "subestacion_alimentador": "271-CAnUELAS / R:271-1-14 / 271-1-14",
      "usuarios": "8",
      "normalizacion": "Sin datos"
    },
    {
      "partido": "ESTEBAN ECHEVERRIA",
      "localidad": "CANNING EE",
      "subestacion_alimentador": "277-GLEW / R:277-4-44 / 277-4-44",
      "usuarios": "800",
      "normalizacion": "2022-02-25 20:21"
    },
    {
      "partido": "ESTEBAN ECHEVERRIA",
      "localidad": "MONTE GRANDE",
      "subestacion_alimentador": "277-GLEW / R:277-4-44 / 277-4-44",
      "usuarios": "422",
      "normalizacion": "2022-02-25 20:21"
    },
    {
      "partido": "ESTEBAN ECHEVERRIA",
      "localidad": "ZONA RURAL 1 EE",
      "subestacion_alimentador": "277-GLEW / R:277-4-44 / 277-4-44",
      "usuarios": "37",
      "normalizacion": "2022-02-25 20:21"
    },
    {
      "partido": "EZEIZA",
      "localidad": "CANNING EZ",
      "subestacion_alimentador": "277-GLEW / R:277-4-44 / 277-4-44",
      "usuarios": "863",
      "normalizacion": "2022-02-25 20:21"
    },
    {
      "partido": "EZEIZA",
      "localidad": "JOSE MARIA EZEIZA",
      "subestacion_alimentador": "277-GLEW / R:277-4-44 / 277-4-44",
      "usuarios": "622",
      "normalizacion": "2022-02-25 20:21"
    },
    {
      "partido": "PTE PERON",
      "localidad": "AMERICA UNIDA",
      "subestacion_alimentador": "277-GLEW / R:277-4-44 / 277-4-44",
      "usuarios": "95",
      "normalizacion": "2022-02-25 20:21"
    },
    {
      "partido": "PTE PERON",
      "localidad": "ZONA RURAL I PP",
      "subestacion_alimentador": "277-GLEW / R:277-4-44 / 277-4-44",
      "usuarios": "331",
      "normalizacion": "2022-02-25 20:21"
    }
  ],
  "cortesComunicados": [],
  "cortesServicioBaja": [
    {
      "partido": "ALMIRANTE BROWN",
      "localidad": "GLEW",
      "usuarios": "10"
    },
    {
      "partido": "CAPITAL",
      "localidad": "BOEDO",
      "usuarios": "14"
    },
    {
      "partido": "CAPITAL",
      "localidad": "PARQUE CHACABUCO",
      "usuarios": "12"
    },
    {
      "partido": "CAPITAL",
      "localidad": "VILLA DEL PARQUE",
      "usuarios": "141"
    }
  ]
}
