{
  "fuente": "Web Service",
  "empresa": "EDESUR",
  "totalUsuariosSinSuministro": "999",
  "totalUsuariosConSuministro": "2.533.181",
  "ultimaActualizacion": "7:35",
  "totalUsuariosAyer": "7.875",
  "cortesPreventivos": [],
  "cortesProgramados": [],
  "cortesServicioMedia": [
    {
      "partido": "CAPITAL FEDERAL",
      "localidad": "CONSTITUCION",
      "subestacion_alimentador": "124-CONSTITUCION / R:124-2-24 / 124-2-24",
      "usuarios": "528",
      "normalizacion": "2022-04-03 08:53"
    },
    {
      "partido": "ESTEBAN ECHEVERRIA",
      "localidad": "CANNING EE",
      "subestacion_alimentador": "83-ECHEVERRIA / R:083-4-45 / 083-4-45",
      "usuarios": "423",
      "normalizacion": "2022-04-03 07:57"
    },
    {
      "partido": "ESTEBAN ECHEVERRIA",
      "localidad": "MONTE GRANDE",
      "subestacion_alimentador": "83-ECHEVERRIA / R:083-4-45 / 083-4-45",
      "usuarios": "8",
      "normalizacion": "2022-04-03 07:57"
    }
  ],
  "cortesComunicados": [],
  "cortesServicioBaja": [
    {
      "partido": "CAPITAL",
      "localidad": "PARQUE AVELLANEDA",
      "usuarios": "25"
    },
    {
      "partido": "PTE PERON",
      "localidad": "GUERNICA",
      "usuarios": "8"
    },
    {
      "partido": "SAN VICENTE",
      "localidad": "SAN VICENTE",
      "usuarios": "7"
    }
  ]
}
