{
  "fuente": "Web Service",
  "empresa": "EDESUR",
  "totalUsuariosSinSuministro": "12.369",
  "totalUsuariosConSuministro": "2.521.216",
  "ultimaActualizacion": "16:50",
  "totalUsuariosAyer": "17.334",
  "cortesPreventivos": [],
  "cortesProgramados": [
    {
      "partido": "CAPITAL FEDERAL",
      "localidad": "ALMAGRO",
      "subestacion_alimentador": "49-PARQUE CENTENARIO / R:049-2-24 / 049-2-24",
      "usuarios": "107",
      "normalizacion": "2022-05-15 20:36"
    },
    {
      "partido": "ESTEBAN ECHEVERRIA",
      "localidad": "EL JAGUEL",
      "subestacion_alimentador": "83-ECHEVERRIA / R:083-3-31 / 083-3-31",
      "usuarios": "582",
      "normalizacion": "Sin datos"
    }
  ],
  "cortesServicioMedia": [
    {
      "partido": "ALMIRANTE BROWN",
      "localidad": "ADROGUE",
      "subestacion_alimentador": "82-BURZACO / R:082-1-01 / 082-1-01",
      "usuarios": "1784",
      "normalizacion": "2022-05-15 21:59"
    },
    {
      "partido": "ALMIRANTE BROWN",
      "localidad": "BURZACO",
      "subestacion_alimentador": "82-BURZACO / R:082-1-01 / 082-1-01",
      "usuarios": "351",
      "normalizacion": "2022-05-15 21:59"
    },
    {
      "partido": "CAÑUELAS",
      "localidad": "ZONA RURAL 7",
      "subestacion_alimentador": "271-CAnUELAS / R:271-3-72 / 271-3-72",
      "usuarios": "3",
      "normalizacion": "2022-05-15 19:46"
    },
    {
      "partido": "CAPITAL FEDERAL",
      "localidad": "PARQUE PATRICIOS",
      "subestacion_alimentador": "15-PATRICIOS / R:015-1-13 / 015-1-13",
      "usuarios": "124",
      "normalizacion": "2022-05-15 19:14"
    },
    {
      "partido": "CAPITAL FEDERAL",
      "localidad": "VILLA LUGANO",
      "subestacion_alimentador": "42-AUTODROMO / R:042-2-25 / 042-2-25",
      "usuarios": "2",
      "normalizacion": "2022-05-15 19:59"
    },
    {
      "partido": "LANUS",
      "localidad": "MONTE CHINGOLO",
      "subestacion_alimentador": "87-ESCALADA / R:087-1-0910 / 087-1-0910",
      "usuarios": "694",
      "normalizacion": "Sin datos"
    },
    {
      "partido": "SAN VICENTE",
      "localidad": "ALEJANDRO KORN",
      "subestacion_alimentador": "271-CAnUELAS / R:271-3-72 / 271-3-72",
      "usuarios": "1168",
      "normalizacion": "2022-05-15 19:46"
    },
    {
      "partido": "SAN VICENTE",
      "localidad": "DOMSELAAR",
      "subestacion_alimentador": "271-CAnUELAS / R:271-3-72 / 271-3-72",
      "usuarios": "9",
      "normalizacion": "2022-05-15 19:46"
    },
    {
      "partido": "SAN VICENTE",
      "localidad": "DOMSELAAR",
      "subestacion_alimentador": "271-CAnUELAS / R:271-4-81 / 271-4-81",
      "usuarios": "7",
      "normalizacion": "2022-05-15 19:59"
    },
    {
      "partido": "SAN VICENTE",
      "localidad": "SAN VICENTE",
      "subestacion_alimentador": "271-CAnUELAS / R:271-4-81 / 271-4-81",
      "usuarios": "2066",
      "normalizacion": "2022-05-15 19:59"
    },
    {
      "partido": "SAN VICENTE",
      "localidad": "SAN VICENTE",
      "subestacion_alimentador": "271-CAnUELAS / R:271-3-72 / 271-3-72",
      "usuarios": "5332",
      "normalizacion": "2022-05-15 19:46"
    }
  ],
  "cortesComunicados": [],
  "cortesServicioBaja": [
    {
      "partido": "ALMIRANTE BROWN",
      "localidad": "SAN JOSE",
      "usuarios": "18"
    },
    {
      "partido": "CAPITAL",
      "localidad": "ALMAGRO",
      "usuarios": "43"
    },
    {
      "partido": "CAPITAL",
      "localidad": "CAPITAL",
      "usuarios": "1"
    },
    {
      "partido": "CAPITAL",
      "localidad": "VELEZ SARFIELD",
      "usuarios": "48"
    },
    {
      "partido": "CAPITAL",
      "localidad": "VILLA STA. RITA",
      "usuarios": "5"
    },
    {
      "partido": "FLORENCIO VARELA",
      "localidad": "FLORENCIO VARELA",
      "usuarios": "4"
    },
    {
      "partido": "LOMAS DE ZAMORA",
      "localidad": "INGENIERO BUDGE",
      "usuarios": "5"
    },
    {
      "partido": "LOMAS DE ZAMORA",
      "localidad": "TEMPERLEY",
      "usuarios": "3"
    },
    {
      "partido": "SAN VICENTE",
      "localidad": "SAN VICENTE",
      "usuarios": "13"
    }
  ]
}
