{
  "fuente": "Web Service",
  "empresa": "EDESUR",
  "totalUsuariosSinSuministro": "881",
  "totalUsuariosConSuministro": "2.532.704",
  "ultimaActualizacion": "22:30",
  "totalUsuariosAyer": "9.250",
  "cortesPreventivos": [],
  "cortesProgramados": [
    {
      "partido": "LOMAS DE ZAMORA",
      "localidad": "TEMPERLEY",
      "subestacion_alimentador": "184-MONTE CHINGOLO / R:184-4-42 / 184-4-42",
      "usuarios": "745",
      "normalizacion": "2022-05-09 00:33"
    }
  ],
  "cortesServicioMedia": [],
  "cortesComunicados": [],
  "cortesServicioBaja": [
    {
      "partido": "CAPITAL",
      "localidad": "CAPITAL",
      "usuarios": "43"
    },
    {
      "partido": "CAPITAL",
      "localidad": "FLORES",
      "usuarios": "41"
    },
    {
      "partido": "CAPITAL",
      "localidad": "SAN NICOLAS",
      "usuarios": "29"
    },
    {
      "partido": "CAPITAL",
      "localidad": "VILLA LUGANO",
      "usuarios": "23"
    }
  ]
}
