{
  "fuente": "Web Service",
  "empresa": "EDESUR",
  "totalUsuariosSinSuministro": "874",
  "totalUsuariosConSuministro": "2.532.711",
  "ultimaActualizacion": "22:35",
  "totalUsuariosAyer": "29.857",
  "cortesPreventivos": [],
  "cortesProgramados": [],
  "cortesServicioMedia": [],
  "cortesComunicados": [],
  "cortesServicioBaja": [
    {
      "partido": "ALMIRANTE BROWN",
      "localidad": "GLEW",
      "usuarios": "39"
    },
    {
      "partido": "ALMIRANTE BROWN",
      "localidad": "LONGCHAMPS",
      "usuarios": "14"
    },
    {
      "partido": "ALMIRANTE BROWN",
      "localidad": "MARMOL",
      "usuarios": "6"
    },
    {
      "partido": "ALMIRANTE BROWN",
      "localidad": "RAFAEL CALZADA",
      "usuarios": "10"
    },
    {
      "partido": "BERAZATEGUI",
      "localidad": "EL PATO",
      "usuarios": "21"
    },
    {
      "partido": "BERAZATEGUI",
      "localidad": "SOURIGUES",
      "usuarios": "1"
    },
    {
      "partido": "CAPITAL",
      "localidad": "BARRACAS",
      "usuarios": "27"
    },
    {
      "partido": "CAPITAL",
      "localidad": "CABALLITO",
      "usuarios": "12"
    },
    {
      "partido": "CAPITAL",
      "localidad": "CAPITAL",
      "usuarios": "25"
    },
    {
      "partido": "CAPITAL",
      "localidad": "FLORES",
      "usuarios": "25"
    },
    {
      "partido": "CAPITAL",
      "localidad": "LINIERS",
      "usuarios": "24"
    },
    {
      "partido": "CAPITAL",
      "localidad": "NUEVA POMPEYA",
      "usuarios": "24"
    },
    {
      "partido": "CAPITAL",
      "localidad": "VILLA DEVOTO",
      "usuarios": "42"
    },
    {
      "partido": "CAPITAL",
      "localidad": "VILLA LUGANO",
      "usuarios": "20"
    },
    {
      "partido": "CAPITAL",
      "localidad": "VILLA RIACHUELO",
      "usuarios": "9"
    },
    {
      "partido": "ESTEBAN ECHEVERRIA",
      "localidad": "EL JAGUEL",
      "usuarios": "26"
    },
    {
      "partido": "FLORENCIO VARELA",
      "localidad": "BOSQUES",
      "usuarios": "75"
    },
    {
      "partido": "FLORENCIO VARELA",
      "localidad": "FLORENCIO VARELA",
      "usuarios": "11"
    },
    {
      "partido": "LOMAS DE ZAMORA",
      "localidad": "INGENIERO BUDGE",
      "usuarios": "214"
    },
    {
      "partido": "LOMAS DE ZAMORA",
      "localidad": "LOMAS DE ZAMORA",
      "usuarios": "42"
    },
    {
      "partido": "LOMAS DE ZAMORA",
      "localidad": "VILLA CENTENARIO",
      "usuarios": "83"
    },
    {
      "partido": "LOMAS DE ZAMORA",
      "localidad": "VILLA FIORITO",
      "usuarios": "16"
    },
    {
      "partido": "PTE PERON",
      "localidad": "PARQUE AMERICANO",
      "usuarios": "20"
    },
    {
      "partido": "PTE PERON",
      "localidad": "PARQUE LAS NACIONES",
      "usuarios": "12"
    },
    {
      "partido": "QUILMES",
      "localidad": "BERNAL",
      "usuarios": "16"
    },
    {
      "partido": "QUILMES",
      "localidad": "QUILMES",
      "usuarios": "21"
    },
    {
      "partido": "QUILMES",
      "localidad": "SAN FRANCISCO SOLANO (Q)",
      "usuarios": "39"
    }
  ]
}
