{
  "fuente": "Web Service",
  "empresa": "EDESUR",
  "totalUsuariosSinSuministro": "7.106",
  "totalUsuariosConSuministro": "2.526.479",
  "ultimaActualizacion": "23:55",
  "totalUsuariosAyer": "35.939",
  "cortesPreventivos": [],
  "cortesProgramados": [
    {
      "partido": "CAPITAL FEDERAL",
      "localidad": "CABALLITO RP",
      "subestacion_alimentador": "122-CABALLITO / R:122-2-28 / 122-2-28",
      "usuarios": "196",
      "normalizacion": "Sin datos"
    }
  ],
  "cortesServicioMedia": [
    {
      "partido": "ALMIRANTE BROWN",
      "localidad": "SAN FRANCISCO SOLANO",
      "subestacion_alimentador": "189-RAFAEL CALZADA / R:189-2-26 / 189-2-26",
      "usuarios": "1528",
      "normalizacion": "2022-07-03 05:21"
    },
    {
      "partido": "BERAZATEGUI",
      "localidad": "EL PATO",
      "subestacion_alimentador": "174-GUTIERREZ II / R:174-1-12 / 174-1-12",
      "usuarios": "20",
      "normalizacion": "2022-07-03 05:21"
    },
    {
      "partido": "CAPITAL FEDERAL",
      "localidad": "MATADEROS",
      "subestacion_alimentador": "43-LINIERS / R:043-1-16 / 043-1-16",
      "usuarios": "2896",
      "normalizacion": "2022-07-03 03:21"
    },
    {
      "partido": "EZEIZA",
      "localidad": "JOSE MARIA EZEIZA",
      "subestacion_alimentador": "270-SPEGAZZINI / R:270-1-18 / 270-1-18 / 083-1-11",
      "usuarios": "7",
      "normalizacion": "2022-07-03 05:24"
    },
    {
      "partido": "QUILMES",
      "localidad": "SAN FRANCISCO SOLANO (Q)",
      "subestacion_alimentador": "184-MONTE CHINGOLO / R:184-3-35 / 184-3-35",
      "usuarios": "2054",
      "normalizacion": "2022-07-03 04:48"
    }
  ],
  "cortesComunicados": [],
  "cortesServicioBaja": [
    {
      "partido": "ALMIRANTE BROWN",
      "localidad": "ADROGUE",
      "usuarios": "19"
    },
    {
      "partido": "ALMIRANTE BROWN",
      "localidad": "GLEW",
      "usuarios": "35"
    },
    {
      "partido": "ALMIRANTE BROWN",
      "localidad": "RAFAEL CALZADA",
      "usuarios": "1"
    },
    {
      "partido": "AVELLANEDA",
      "localidad": "AVELLANEDA",
      "usuarios": "46"
    },
    {
      "partido": "BERAZATEGUI",
      "localidad": "BERAZATEGUI",
      "usuarios": "31"
    },
    {
      "partido": "CAPITAL",
      "localidad": "MATADEROS",
      "usuarios": "6"
    },
    {
      "partido": "CAPITAL",
      "localidad": "VILLA DEVOTO",
      "usuarios": "21"
    },
    {
      "partido": "CAPITAL",
      "localidad": "VILLA LUGANO",
      "usuarios": "30"
    },
    {
      "partido": "ESTEBAN ECHEVERRIA",
      "localidad": "LUIS GUILLON",
      "usuarios": "32"
    },
    {
      "partido": "ESTEBAN ECHEVERRIA",
      "localidad": "MONTE GRANDE",
      "usuarios": "15"
    },
    {
      "partido": "FLORENCIO VARELA",
      "localidad": "FLORENCIO VARELA",
      "usuarios": "76"
    },
    {
      "partido": "LANUS",
      "localidad": "LANUS",
      "usuarios": "9"
    },
    {
      "partido": "LOMAS DE ZAMORA",
      "localidad": "INGENIERO BUDGE",
      "usuarios": "48"
    },
    {
      "partido": "QUILMES",
      "localidad": "QUILMES",
      "usuarios": "10"
    },
    {
      "partido": "QUILMES",
      "localidad": "SAN FRANCISCO SOLANO (Q)",
      "usuarios": "26"
    }
  ]
}
