{
  "fuente": "Web Service",
  "empresa": "EDESUR",
  "totalUsuariosSinSuministro": "2.724",
  "totalUsuariosConSuministro": "2.531.456",
  "ultimaActualizacion": "16:30",
  "totalUsuariosAyer": "36.264",
  "cortesPreventivos": [],
  "cortesProgramados": [
    {
      "partido": "CAPITAL FEDERAL",
      "localidad": "VILLA CRESPO",
      "subestacion_alimentador": "143-SANTA RITA / R:143-2-24 / 143-2-24 / 143-1-14",
      "usuarios": "331",
      "normalizacion": "2022-01-28 00:10"
    },
    {
      "partido": "LOMAS DE ZAMORA",
      "localidad": "LOMAS DE ZAMORA",
      "subestacion_alimentador": "76-HEROES DE MALVINAS / R:076-1-15 / 076-1-15",
      "usuarios": "872",
      "normalizacion": "2022-01-27 19:16"
    },
    {
      "partido": "LOMAS DE ZAMORA",
      "localidad": "TEMPERLEY",
      "subestacion_alimentador": "76-HEROES DE MALVINAS / R:076-1-15 / 076-1-15",
      "usuarios": "503",
      "normalizacion": "2022-01-27 19:16"
    }
  ],
  "cortesServicioMedia": [
    {
      "partido": "FLORENCIO VARELA",
      "localidad": "FLORENCIO VARELA",
      "subestacion_alimentador": "286- / R:286-5-58 / 286-5-58",
      "usuarios": "516",
      "normalizacion": "Sin datos"
    }
  ],
  "cortesComunicados": [],
  "cortesServicioBaja": [
    {
      "partido": "ALMIRANTE BROWN",
      "localidad": "LONGCHAMPS",
      "usuarios": "10"
    },
    {
      "partido": "BERAZATEGUI",
      "localidad": "BERAZATEGUI",
      "usuarios": "55"
    },
    {
      "partido": "CAPITAL",
      "localidad": "BOEDO",
      "usuarios": "13"
    },
    {
      "partido": "CAPITAL",
      "localidad": "CABALLITO",
      "usuarios": "20"
    },
    {
      "partido": "CAPITAL",
      "localidad": "CAPITAL",
      "usuarios": "96"
    },
    {
      "partido": "CAPITAL",
      "localidad": "PARQUE AVELLANEDA",
      "usuarios": "8"
    },
    {
      "partido": "CAPITAL",
      "localidad": "PARQUE PATRICIOS",
      "usuarios": "31"
    },
    {
      "partido": "CAPITAL",
      "localidad": "SAN NICOLAS",
      "usuarios": "6"
    },
    {
      "partido": "CAPITAL",
      "localidad": "VILLA DEL PARQUE",
      "usuarios": "40"
    },
    {
      "partido": "CAPITAL",
      "localidad": "VILLA DEVOTO",
      "usuarios": "14"
    },
    {
      "partido": "ESTEBAN ECHEVERRIA",
      "localidad": "LUIS GUILLON",
      "usuarios": "21"
    },
    {
      "partido": "ESTEBAN ECHEVERRIA",
      "localidad": "MONTE GRANDE",
      "usuarios": "91"
    },
    {
      "partido": "LANUS",
      "localidad": "VALENTIN ALSINA",
      "usuarios": "12"
    },
    {
      "partido": "QUILMES",
      "localidad": "BERNAL",
      "usuarios": "37"
    },
    {
      "partido": "QUILMES",
      "localidad": "QUILMES",
      "usuarios": "31"
    },
    {
      "partido": "SAN VICENTE",
      "localidad": "SAN VICENTE",
      "usuarios": "17"
    }
  ]
}
