{
  "fuente": "Web Service",
  "empresa": "EDESUR",
  "totalUsuariosSinSuministro": "1.698",
  "totalUsuariosConSuministro": "2.531.887",
  "ultimaActualizacion": "13:20",
  "totalUsuariosAyer": "110.398",
  "cortesPreventivos": [],
  "cortesProgramados": [],
  "cortesServicioMedia": [
    {
      "partido": "CAPITAL FEDERAL",
      "localidad": "PARQUE PATRICIOS",
      "subestacion_alimentador": "20-INDEPENDENCIA / R:020-2-27 / 020-2-27",
      "usuarios": "75",
      "normalizacion": "Sin datos"
    },
    {
      "partido": "CAPITAL FEDERAL",
      "localidad": "SAN CRISTOBAL",
      "subestacion_alimentador": "20-INDEPENDENCIA / R:020-2-27 / 020-2-27",
      "usuarios": "630",
      "normalizacion": "Sin datos"
    }
  ],
  "cortesComunicados": [],
  "cortesServicioBaja": [
    {
      "partido": "ALMIRANTE BROWN",
      "localidad": "GLEW",
      "usuarios": "18"
    },
    {
      "partido": "ALMIRANTE BROWN",
      "localidad": "LONGCHAMPS",
      "usuarios": "18"
    },
    {
      "partido": "ALMIRANTE BROWN",
      "localidad": "SAN JOSE",
      "usuarios": "18"
    },
    {
      "partido": "AVELLANEDA",
      "localidad": "AVELLANEDA",
      "usuarios": "53"
    },
    {
      "partido": "AVELLANEDA",
      "localidad": "SARANDI",
      "usuarios": "62"
    },
    {
      "partido": "CAPITAL",
      "localidad": "LA BOCA",
      "usuarios": "79"
    },
    {
      "partido": "CAPITAL",
      "localidad": "RECOLETA",
      "usuarios": "2"
    },
    {
      "partido": "CAPITAL",
      "localidad": "VILLA LUGANO",
      "usuarios": "19"
    },
    {
      "partido": "ESTEBAN ECHEVERRIA",
      "localidad": "EL JAGUEL",
      "usuarios": "32"
    },
    {
      "partido": "ESTEBAN ECHEVERRIA",
      "localidad": "MONTE GRANDE",
      "usuarios": "20"
    },
    {
      "partido": "EZEIZA",
      "localidad": "CARLOS SPEGAZZINNI",
      "usuarios": "28"
    },
    {
      "partido": "FLORENCIO VARELA",
      "localidad": "BOSQUES",
      "usuarios": "15"
    },
    {
      "partido": "FLORENCIO VARELA",
      "localidad": "ING. ALLAN",
      "usuarios": "22"
    },
    {
      "partido": "LANUS",
      "localidad": "GERLI",
      "usuarios": "1"
    },
    {
      "partido": "LANUS",
      "localidad": "LANUS",
      "usuarios": "54"
    },
    {
      "partido": "LOMAS DE ZAMORA",
      "localidad": "INGENIERO BUDGE",
      "usuarios": "36"
    },
    {
      "partido": "LOMAS DE ZAMORA",
      "localidad": "LOMAS DE ZAMORA",
      "usuarios": "97"
    },
    {
      "partido": "LOMAS DE ZAMORA",
      "localidad": "TEMPERLEY",
      "usuarios": "43"
    },
    {
      "partido": "LOMAS DE ZAMORA",
      "localidad": "VILLA CENTENARIO",
      "usuarios": "53"
    },
    {
      "partido": "LOMAS DE ZAMORA",
      "localidad": "VILLA FIORITO",
      "usuarios": "27"
    },
    {
      "partido": "QUILMES",
      "localidad": "BERNAL",
      "usuarios": "197"
    },
    {
      "partido": "QUILMES",
      "localidad": "EZPELETA",
      "usuarios": "46"
    },
    {
      "partido": "QUILMES",
      "localidad": "QUILMES",
      "usuarios": "53"
    }
  ]
}
