{
  "fuente": "Web Service",
  "empresa": "EDENOR",
  "totalUsuariosSinSuministro": "64",
  "totalUsuariosConSuministro": "2.998.427",
  "ultimaActualizacion": "7:40",
  "totalUsuariosAyer": "22.002",
  "cortesPreventivos": [],
  "cortesProgramados": [],
  "cortesServicioMedia": [
    {
      "partido": "SAN FERNANDO",
      "localidad": "DELTA 2DA SECCION (SF)",
      "subestacion_alimentador": "- / ",
      "usuarios": "35",
      "normalizacion": "2022-03-27 09:00"
    },
    {
      "partido": "TIGRE",
      "localidad": "DON TORCUATO",
      "subestacion_alimentador": "- / R:BANCALARI / 157-TR2 / 157-5525",
      "usuarios": "1",
      "normalizacion": "2022-03-27 09:00"
    }
  ],
  "cortesComunicados": [],
  "cortesServicioBaja": [
    {
      "partido": "MORENO",
      "localidad": "CUARTEL V",
      "usuarios": "28"
    }
  ]
}
