{
  "fuente": "Web Service",
  "empresa": "EDENOR",
  "totalUsuariosSinSuministro": "6.397",
  "totalUsuariosConSuministro": "2.992.094",
  "ultimaActualizacion": "6:50",
  "totalUsuariosAyer": "41.223",
  "cortesPreventivos": [],
  "cortesProgramados": [],
  "cortesServicioMedia": [
    {
      "partido": "",
      "localidad": "",
      "subestacion_alimentador": "- / R:LUZURIAGA / 64-TR1 / 64-5514",
      "usuarios": "91",
      "normalizacion": "2022-01-01 08:00"
    },
    {
      "partido": "",
      "localidad": "",
      "subestacion_alimentador": "- / R:PILAR / 158-TR3 / 158-5473",
      "usuarios": "1",
      "normalizacion": "2022-01-01 07:00"
    },
    {
      "partido": "CAPITAL FEDERAL",
      "localidad": "PALERMO",
      "subestacion_alimentador": "- / R:MELO / 237-TR2 / 237-5533",
      "usuarios": "16",
      "normalizacion": "Sin datos"
    },
    {
      "partido": "CAPITAL FEDERAL",
      "localidad": "VILLA PUEYRRED?N",
      "subestacion_alimentador": "- / R:AGRONOMIA / 47-TR5 / 47-5561",
      "usuarios": "607",
      "normalizacion": "2022-01-01 08:00"
    },
    {
      "partido": "GRAL RODRIGUEZ",
      "localidad": "GRAL RODRIGUEZ",
      "subestacion_alimentador": "- / R:MALVINAS / 169-TR2 / 169-5476 / 255-5522",
      "usuarios": "1417",
      "normalizacion": "2022-01-01 08:00"
    },
    {
      "partido": "LA MATANZA",
      "localidad": "RAFAEL CASTILLO",
      "subestacion_alimentador": "- / R:LUZURIAGA / 64-TR1 / 64-5514",
      "usuarios": "595",
      "normalizacion": "2022-01-01 08:00"
    },
    {
      "partido": "LA MATANZA",
      "localidad": "RAMOS MEJIA",
      "subestacion_alimentador": "- / R:RAMOS MEJIA / 66-TR1 / 66-5513",
      "usuarios": "152",
      "normalizacion": "2022-01-01 08:00"
    },
    {
      "partido": "PILAR",
      "localidad": "DEL VISO",
      "subestacion_alimentador": "- / R:DELVISO / 251-TR1 / 251-5545",
      "usuarios": "692",
      "normalizacion": "2022-01-01 08:00"
    },
    {
      "partido": "PILAR",
      "localidad": "FATIMA",
      "subestacion_alimentador": "- / R:PILAR / 158-TR3 / 158-5473",
      "usuarios": "11",
      "normalizacion": "2022-01-01 07:00"
    },
    {
      "partido": "PILAR",
      "localidad": "PILAR",
      "subestacion_alimentador": "- / R:PILAR / 158-TR3 / 158-5473",
      "usuarios": "1",
      "normalizacion": "2022-01-01 07:00"
    },
    {
      "partido": "PILAR",
      "localidad": "VILLA ROSA",
      "subestacion_alimentador": "- / R:MATHEU / 51-TR1 / 51-5511",
      "usuarios": "264",
      "normalizacion": "2022-01-01 08:00"
    },
    {
      "partido": "SAN MIGUEL",
      "localidad": "BELLA VISTA",
      "subestacion_alimentador": "- / R:MORON / 67-TR4 / 67-5527",
      "usuarios": "2218",
      "normalizacion": "2022-01-01 07:00"
    },
    {
      "partido": "SAN MIGUEL",
      "localidad": "CAMPO DE MAYO",
      "subestacion_alimentador": "- / R:MORON / 67-TR4 / 67-5527",
      "usuarios": "54",
      "normalizacion": "2022-01-01 07:00"
    }
  ],
  "cortesComunicados": [],
  "cortesServicioBaja": [
    {
      "partido": "CAPITAL FEDERAL",
      "localidad": "VILLA ORTUZAR",
      "usuarios": "28"
    },
    {
      "partido": "CAPITAL FEDERAL",
      "localidad": "VILLA URQUIZA",
      "usuarios": "30"
    },
    {
      "partido": "LA MATANZA",
      "localidad": "ISIDRO CASANOVA",
      "usuarios": "24"
    },
    {
      "partido": "LA MATANZA",
      "localidad": "VILLA MADERO",
      "usuarios": "22"
    },
    {
      "partido": "MALVINAS ARGENTINAS",
      "localidad": "GRAND BOURG",
      "usuarios": "47"
    },
    {
      "partido": "MERLO",
      "localidad": "MARIANO ACOSTA",
      "usuarios": "21"
    },
    {
      "partido": "MORENO",
      "localidad": "CUARTEL V",
      "usuarios": "19"
    },
    {
      "partido": "MORENO",
      "localidad": "PASO DEL REY",
      "usuarios": "19"
    },
    {
      "partido": "MORON",
      "localidad": "MORON",
      "usuarios": "1"
    },
    {
      "partido": "PILAR",
      "localidad": "VILLA ROSA",
      "usuarios": "17"
    },
    {
      "partido": "SAN MIGUEL",
      "localidad": "SAN MIGUEL",
      "usuarios": "19"
    },
    {
      "partido": "TIGRE",
      "localidad": "RICARDO ROJAS",
      "usuarios": "4"
    },
    {
      "partido": "TIGRE",
      "localidad": "RINCON DE MILBERG",
      "usuarios": "27"
    }
  ]
}
