{
  "fuente": "Web Service",
  "empresa": "EDENOR",
  "totalUsuariosSinSuministro": "1.217",
  "totalUsuariosConSuministro": "2.997.274",
  "ultimaActualizacion": "5:10",
  "totalUsuariosAyer": "11.414",
  "cortesPreventivos": [],
  "cortesProgramados": [],
  "cortesServicioMedia": [
    {
      "partido": "LA MATANZA",
      "localidad": "ALDO BONZI",
      "subestacion_alimentador": "- / R:TAPIALES / 162-TR2 / 162-5534",
      "usuarios": "1143",
      "normalizacion": "2022-02-09 06:00"
    }
  ],
  "cortesComunicados": [],
  "cortesServicioBaja": [
    {
      "partido": "CAPITAL FEDERAL",
      "localidad": "NU?EZ",
      "usuarios": "31"
    },
    {
      "partido": "LA MATANZA",
      "localidad": "ALDO BONZI",
      "usuarios": "18"
    },
    {
      "partido": "LA MATANZA",
      "localidad": "CIUDAD EVITA",
      "usuarios": "19"
    },
    {
      "partido": "SAN MIGUEL",
      "localidad": "SAN MIGUEL",
      "usuarios": "6"
    }
  ]
}
