{
  "fuente": "Web Service",
  "empresa": "EDENOR",
  "totalUsuariosSinSuministro": "141",
  "totalUsuariosConSuministro": "3.199.930",
  "ultimaActualizacion": "7:40",
  "totalUsuariosAyer": "10.943",
  "cortesPreventivos": [],
  "cortesProgramados": [],
  "cortesServicioMedia": [],
  "cortesComunicados": [],
  "cortesServicioBaja": [
    {
      "partido": "GRAL RODRIGUEZ",
      "localidad": "GRAL RODRIGUEZ",
      "usuarios": "25"
    },
    {
      "partido": "GRAL SAN MARTIN",
      "localidad": "VILLA MAIPU",
      "usuarios": "16"
    },
    {
      "partido": "MORENO",
      "localidad": "PASO DEL REY",
      "usuarios": "22"
    },
    {
      "partido": "VICENTE LOPEZ",
      "localidad": "MUNRO",
      "usuarios": "78"
    }
  ]
}
