{
  "fuente": "Web Service",
  "empresa": "EDENOR",
  "totalUsuariosSinSuministro": "1.899",
  "totalUsuariosConSuministro": "2.996.592",
  "ultimaActualizacion": "19:45",
  "totalUsuariosAyer": "19.030",
  "cortesPreventivos": [],
  "cortesProgramados": [],
  "cortesServicioMedia": [
    {
      "partido": "CAPITAL FEDERAL",
      "localidad": "LA PATERNAL",
      "subestacion_alimentador": "- / R:AGRONOMIA / 47-TR3 / 47-5544",
      "usuarios": "1",
      "normalizacion": "2022-04-21 22:00"
    },
    {
      "partido": "MORENO",
      "localidad": "FRANCISCO ALVAREZ",
      "subestacion_alimentador": "- / R:GAONA / 263-TR2",
      "usuarios": "1795",
      "normalizacion": "2022-04-21 20:00"
    }
  ],
  "cortesComunicados": [],
  "cortesServicioBaja": [
    {
      "partido": "CAPITAL FEDERAL",
      "localidad": "PALERMO",
      "usuarios": "4"
    },
    {
      "partido": "ESCOBAR",
      "localidad": "INGENIERO MASCHWITZ",
      "usuarios": "20"
    },
    {
      "partido": "GRAL RODRIGUEZ",
      "localidad": "GRAL RODRIGUEZ",
      "usuarios": "6"
    },
    {
      "partido": "LA MATANZA",
      "localidad": "RAMOS MEJIA",
      "usuarios": "1"
    },
    {
      "partido": "LA MATANZA",
      "localidad": "VIRREY DEL PINO",
      "usuarios": "17"
    },
    {
      "partido": "PILAR",
      "localidad": "MANUEL ALBERTI",
      "usuarios": "22"
    },
    {
      "partido": "SAN MIGUEL",
      "localidad": "BELLA VISTA",
      "usuarios": "33"
    }
  ]
}
