{
  "fuente": "Web Service",
  "empresa": "EDENOR",
  "totalUsuariosSinSuministro": "1.234",
  "totalUsuariosConSuministro": "2.997.257",
  "ultimaActualizacion": "2:40",
  "totalUsuariosAyer": "43.185",
  "cortesPreventivos": [],
  "cortesProgramados": [],
  "cortesServicioMedia": [
    {
      "partido": "ESCOBAR",
      "localidad": "GARIN",
      "subestacion_alimentador": "- / R:BENAVIDEZ / 59-TR4 / 59-5545",
      "usuarios": "708",
      "normalizacion": "2022-01-03 04:00"
    },
    {
      "partido": "TIGRE",
      "localidad": "BENAVIDEZ",
      "subestacion_alimentador": "- / R:BENAVIDEZ / 59-TR4 / 59-5547",
      "usuarios": "233",
      "normalizacion": "2022-01-03 04:00"
    }
  ],
  "cortesComunicados": [],
  "cortesServicioBaja": [
    {
      "partido": "CAPITAL FEDERAL",
      "localidad": "PALERMO",
      "usuarios": "6"
    },
    {
      "partido": "CAPITAL FEDERAL",
      "localidad": "VILLA ORTUZAR",
      "usuarios": "14"
    },
    {
      "partido": "ESCOBAR",
      "localidad": "INGENIERO MASCHWITZ",
      "usuarios": "27"
    },
    {
      "partido": "GRAL RODRIGUEZ",
      "localidad": "GRAL RODRIGUEZ",
      "usuarios": "23"
    },
    {
      "partido": "GRAL SAN MARTIN",
      "localidad": "VILLA LIBERTAD",
      "usuarios": "26"
    },
    {
      "partido": "JOSE C PAZ",
      "localidad": "JOSE C PAZ",
      "usuarios": "39"
    },
    {
      "partido": "LA MATANZA",
      "localidad": "GREGORIO DE LAFERRERE",
      "usuarios": "12"
    },
    {
      "partido": "LA MATANZA",
      "localidad": "SAN JUSTO",
      "usuarios": "4"
    },
    {
      "partido": "MALVINAS ARGENTINAS",
      "localidad": "EL TRIANGULO",
      "usuarios": "4"
    },
    {
      "partido": "MERLO",
      "localidad": "MERLO",
      "usuarios": "37"
    },
    {
      "partido": "MORENO",
      "localidad": "LA REJA",
      "usuarios": "4"
    },
    {
      "partido": "MORENO",
      "localidad": "PASO DEL REY",
      "usuarios": "19"
    },
    {
      "partido": "SAN FERNANDO",
      "localidad": "VIRREYES",
      "usuarios": "36"
    },
    {
      "partido": "TIGRE",
      "localidad": "EL TALAR",
      "usuarios": "15"
    },
    {
      "partido": "TIGRE",
      "localidad": "RINCON DE MILBERG",
      "usuarios": "27"
    }
  ]
}
