{
  "fuente": "Web Service",
  "empresa": "EDENOR",
  "totalUsuariosSinSuministro": "3.787",
  "totalUsuariosConSuministro": "3.196.284",
  "ultimaActualizacion": "9:55",
  "totalUsuariosAyer": "18.347",
  "cortesPreventivos": [],
  "cortesProgramados": [
    {
      "partido": "3 DE FEBRERO",
      "localidad": "SANTOS LUGARES",
      "subestacion_alimentador": "- / R:MIGUELETES / 54-TR1 / 54-5518",
      "usuarios": "284",
      "normalizacion": "2022-06-28 10:00"
    },
    {
      "partido": "3 DE FEBRERO",
      "localidad": "VILLA RAFFO",
      "subestacion_alimentador": "- / R:CIUDADELA / 167-TR2 / 167-5533",
      "usuarios": "305",
      "normalizacion": "2022-06-28 10:00"
    },
    {
      "partido": "GRAL LAS HERAS",
      "localidad": "GRAL LAS HERAS",
      "subestacion_alimentador": "- / R:MARCOS PAZ / 363-TR4 / 363-5481 / 132-5512",
      "usuarios": "183",
      "normalizacion": "2022-06-28 11:00"
    },
    {
      "partido": "GRAL SAN MARTIN",
      "localidad": "C JARDIN EL LIBERTADOR",
      "subestacion_alimentador": "- / R:ROTONDA / 262-TR1 / 262-5516",
      "usuarios": "2",
      "normalizacion": "2022-06-28 10:00"
    },
    {
      "partido": "LA MATANZA",
      "localidad": "VIRREY DEL PINO",
      "subestacion_alimentador": "- / R:EL PINO / 353-TR1 / 353-5515",
      "usuarios": "1127",
      "normalizacion": "2022-06-28 10:00"
    },
    {
      "partido": "LA MATANZA",
      "localidad": "VIRREY DEL PINO",
      "subestacion_alimentador": "- / R:GONZALEZ CATAN / 168-TR1 / 168-5471",
      "usuarios": "419",
      "normalizacion": "2022-06-28 11:00"
    }
  ],
  "cortesServicioMedia": [
    {
      "partido": "ESCOBAR",
      "localidad": "INGENIERO MASCHWITZ",
      "subestacion_alimentador": "- / R:MASCHWITZ / 154-TR1 / 154-5511",
      "usuarios": "175",
      "normalizacion": "2022-06-28 10:00"
    },
    {
      "partido": "LA MATANZA",
      "localidad": "VIRREY DEL PINO",
      "subestacion_alimentador": "- / R:GONZALEZ CATAN / 168-TR1 / 168-5511",
      "usuarios": "31",
      "normalizacion": "2022-06-28 11:00"
    },
    {
      "partido": "MORENO",
      "localidad": "LA REJA",
      "subestacion_alimentador": "- / R:GAONA / 263-TR1 / 263-5516",
      "usuarios": "103",
      "normalizacion": "2022-06-28 12:00"
    }
  ],
  "cortesComunicados": [],
  "cortesServicioBaja": [
    {
      "partido": "CAPITAL FEDERAL",
      "localidad": "AGRONOMIA",
      "usuarios": "7"
    },
    {
      "partido": "ESCOBAR",
      "localidad": "ESCOBAR",
      "usuarios": "60"
    },
    {
      "partido": "GRAL SAN MARTIN",
      "localidad": "GREGORIA MATORRAS",
      "usuarios": "54"
    },
    {
      "partido": "HURLINGHAM",
      "localidad": "VILLA TESEI",
      "usuarios": "57"
    },
    {
      "partido": "JOSE C PAZ",
      "localidad": "JOSE C PAZ",
      "usuarios": "100"
    },
    {
      "partido": "LA MATANZA",
      "localidad": "GREGORIO DE LAFERRERE",
      "usuarios": "24"
    },
    {
      "partido": "LA MATANZA",
      "localidad": "LA TABLADA",
      "usuarios": "50"
    },
    {
      "partido": "LA MATANZA",
      "localidad": "SAN JUSTO",
      "usuarios": "29"
    },
    {
      "partido": "LA MATANZA",
      "localidad": "VILLA MADERO",
      "usuarios": "55"
    },
    {
      "partido": "LA MATANZA",
      "localidad": "VIRREY DEL PINO",
      "usuarios": "81"
    },
    {
      "partido": "MALVINAS ARGENTINAS",
      "localidad": "VILLA DE MAYO",
      "usuarios": "8"
    },
    {
      "partido": "MERLO",
      "localidad": "LIBERTAD",
      "usuarios": "47"
    },
    {
      "partido": "MERLO",
      "localidad": "MARIANO ACOSTA",
      "usuarios": "26"
    },
    {
      "partido": "MERLO",
      "localidad": "PONTEVEDRA",
      "usuarios": "39"
    },
    {
      "partido": "MORENO",
      "localidad": "FRANCISCO ALVAREZ",
      "usuarios": "28"
    },
    {
      "partido": "MORENO",
      "localidad": "LA REJA",
      "usuarios": "63"
    },
    {
      "partido": "MORENO",
      "localidad": "MORENO",
      "usuarios": "42"
    },
    {
      "partido": "MORENO",
      "localidad": "TRUJUI",
      "usuarios": "64"
    },
    {
      "partido": "MORON",
      "localidad": "MORON",
      "usuarios": "61"
    },
    {
      "partido": "PILAR",
      "localidad": "DEL VISO",
      "usuarios": "4"
    },
    {
      "partido": "PILAR",
      "localidad": "LA LONJA",
      "usuarios": "1"
    },
    {
      "partido": "PILAR",
      "localidad": "LUIS LAGOMARSINO",
      "usuarios": "24"
    },
    {
      "partido": "PILAR",
      "localidad": "MANUEL ALBERTI",
      "usuarios": "8"
    },
    {
      "partido": "PILAR",
      "localidad": "PILAR",
      "usuarios": "35"
    },
    {
      "partido": "PILAR",
      "localidad": "PTE DERQUI",
      "usuarios": "23"
    },
    {
      "partido": "PILAR",
      "localidad": "VILLA ASTOLFI",
      "usuarios": "29"
    },
    {
      "partido": "SAN FERNANDO",
      "localidad": "VIRREYES",
      "usuarios": "41"
    },
    {
      "partido": "SAN MIGUEL",
      "localidad": "BELLA VISTA",
      "usuarios": "36"
    },
    {
      "partido": "TIGRE",
      "localidad": "DIQUE LUJAN",
      "usuarios": "62"
    }
  ]
}
