{
  "fuente": "Web Service",
  "empresa": "EDENOR",
  "totalUsuariosSinSuministro": "4.234",
  "totalUsuariosConSuministro": "2.994.257",
  "ultimaActualizacion": "23:15",
  "totalUsuariosAyer": "18.055",
  "cortesPreventivos": [],
  "cortesProgramados": [],
  "cortesServicioMedia": [
    {
      "partido": "MARCOS PAZ",
      "localidad": "MARCOS PAZ",
      "subestacion_alimentador": "- / R:MARCOS PAZ / 363-TR2 / 363-5526",
      "usuarios": "5",
      "normalizacion": "2022-02-20 00:00"
    },
    {
      "partido": "MERLO",
      "localidad": "MERLO",
      "subestacion_alimentador": "- / R:PONTEVEDRA / 261-TR1 / 261-5518",
      "usuarios": "2692",
      "normalizacion": "2022-02-20 01:00"
    },
    {
      "partido": "MERLO",
      "localidad": "PONTEVEDRA",
      "subestacion_alimentador": "- / R:PONTEVEDRA / 261-TR1 / 261-5518",
      "usuarios": "1279",
      "normalizacion": "2022-02-20 01:00"
    }
  ],
  "cortesComunicados": [],
  "cortesServicioBaja": [
    {
      "partido": "GRAL SAN MARTIN",
      "localidad": "YAPEYU",
      "usuarios": "6"
    },
    {
      "partido": "LA MATANZA",
      "localidad": "ISIDRO CASANOVA",
      "usuarios": "1"
    },
    {
      "partido": "MALVINAS ARGENTINAS",
      "localidad": "VILLA DE MAYO",
      "usuarios": "26"
    },
    {
      "partido": "MERLO",
      "localidad": "LIBERTAD",
      "usuarios": "4"
    },
    {
      "partido": "MERLO",
      "localidad": "MARIANO ACOSTA",
      "usuarios": "24"
    },
    {
      "partido": "MORENO",
      "localidad": "LA REJA",
      "usuarios": "33"
    },
    {
      "partido": "MORENO",
      "localidad": "MORENO",
      "usuarios": "4"
    },
    {
      "partido": "PILAR",
      "localidad": "PTE DERQUI",
      "usuarios": "1"
    },
    {
      "partido": "SAN ISIDRO",
      "localidad": "ACASSUSO",
      "usuarios": "65"
    },
    {
      "partido": "TIGRE",
      "localidad": "GENERAL PACHECO",
      "usuarios": "51"
    },
    {
      "partido": "VICENTE LOPEZ",
      "localidad": "VICENTE LOPEZ",
      "usuarios": "43"
    }
  ]
}
