{
  "fuente": "Web Service",
  "empresa": "EDENOR",
  "totalUsuariosSinSuministro": "153",
  "totalUsuariosConSuministro": "3.199.918",
  "ultimaActualizacion": "19:35",
  "totalUsuariosAyer": "14.598",
  "cortesPreventivos": [],
  "cortesProgramados": [],
  "cortesServicioMedia": [],
  "cortesComunicados": [],
  "cortesServicioBaja": [
    {
      "partido": "ESCOBAR",
      "localidad": "INGENIERO MASCHWITZ",
      "usuarios": "23"
    },
    {
      "partido": "GRAL SAN MARTIN",
      "localidad": "C JARDIN EL LIBERTADOR",
      "usuarios": "27"
    },
    {
      "partido": "LA MATANZA",
      "localidad": "ISIDRO CASANOVA",
      "usuarios": "1"
    },
    {
      "partido": "MORENO",
      "localidad": "LA REJA",
      "usuarios": "86"
    },
    {
      "partido": "PILAR",
      "localidad": "PILAR",
      "usuarios": "16"
    }
  ]
}
