{
  "fuente": "Web Service",
  "empresa": "EDENOR",
  "totalUsuariosSinSuministro": "242",
  "totalUsuariosConSuministro": "2.998.249",
  "ultimaActualizacion": "9:15",
  "totalUsuariosAyer": "15.331",
  "cortesPreventivos": [],
  "cortesProgramados": [
    {
      "partido": "GRAL SAN MARTIN",
      "localidad": "M REMEDIOS DE ESCALADA",
      "subestacion_alimentador": "- / R:ROTONDA / 262-TR1 / 262-5542",
      "usuarios": "1",
      "normalizacion": "2022-04-03 10:00"
    },
    {
      "partido": "LA MATANZA",
      "localidad": "GONZALEZ CATAN",
      "subestacion_alimentador": "- / R:PANTANOSA / 365-TR2 / 365-5528",
      "usuarios": "239",
      "normalizacion": "2022-04-03 11:00"
    }
  ],
  "cortesServicioMedia": [],
  "cortesComunicados": [],
  "cortesServicioBaja": [
    {
      "partido": "LA MATANZA",
      "localidad": "GONZALEZ CATAN",
      "usuarios": "2"
    }
  ]
}
