{
  "fuente": "Web Service",
  "empresa": "EDENOR",
  "totalUsuariosSinSuministro": "1.358",
  "totalUsuariosConSuministro": "2.997.133",
  "ultimaActualizacion": "13:00",
  "totalUsuariosAyer": "41.355",
  "cortesPreventivos": [],
  "cortesProgramados": [
    {
      "partido": "3 DE FEBRERO",
      "localidad": "CIUDADELA",
      "subestacion_alimentador": "- / R:CIUDADELA / 167-TR1 / 167-5547",
      "usuarios": "246",
      "normalizacion": "2022-01-31 15:00"
    },
    {
      "partido": "CAPITAL FEDERAL",
      "localidad": "BELGRANO",
      "subestacion_alimentador": "- / R:VIDAL / 114-TR1 / 114-5518",
      "usuarios": "535",
      "normalizacion": "2022-01-31 14:00"
    },
    {
      "partido": "GRAL RODRIGUEZ",
      "localidad": "GRAL RODRIGUEZ",
      "subestacion_alimentador": "- / R:MALVINAS / 169-TR2 / 169-5476 / 255-5523",
      "usuarios": "5",
      "normalizacion": "2022-01-31 14:00"
    },
    {
      "partido": "GRAL RODRIGUEZ",
      "localidad": "GRAL RODRIGUEZ",
      "subestacion_alimentador": "- / R:MALVINAS / 169-TR2 / 169-5542",
      "usuarios": "3",
      "normalizacion": "Sin datos"
    },
    {
      "partido": "MARCOS PAZ",
      "localidad": "MARCOS PAZ",
      "subestacion_alimentador": "- / R:MARCOS PAZ / 363-TR2 / 363-5526",
      "usuarios": "225",
      "normalizacion": "2022-01-31 14:00"
    }
  ],
  "cortesServicioMedia": [
    {
      "partido": "SAN FERNANDO",
      "localidad": "DELTA 2DA SECCION (SF)",
      "subestacion_alimentador": "- / ",
      "usuarios": "5",
      "normalizacion": "2022-01-31 14:00"
    },
    {
      "partido": "TIGRE",
      "localidad": "CIUDAD DE TIGRE",
      "subestacion_alimentador": "- / R:TIGRE / 153-TR2 / 153-5527",
      "usuarios": "310",
      "normalizacion": "2022-01-31 14:00"
    }
  ],
  "cortesComunicados": [],
  "cortesServicioBaja": [
    {
      "partido": "MORENO",
      "localidad": "TRUJUI",
      "usuarios": "29"
    }
  ]
}
