{
  "fuente": "Web Service",
  "empresa": "EDENOR",
  "totalUsuariosSinSuministro": "1.849",
  "totalUsuariosConSuministro": "2.996.642",
  "ultimaActualizacion": "18:45",
  "totalUsuariosAyer": "19.030",
  "cortesPreventivos": [],
  "cortesProgramados": [],
  "cortesServicioMedia": [
    {
      "partido": "ITUZAINGO",
      "localidad": "VILLA UDAONDO",
      "subestacion_alimentador": "- / R:MORON / 67-TR5 / 67-5545",
      "usuarios": "47",
      "normalizacion": "2022-04-21 19:00"
    },
    {
      "partido": "MORENO",
      "localidad": "FRANCISCO ALVAREZ",
      "subestacion_alimentador": "- / R:GAONA / 263-TR2",
      "usuarios": "1795",
      "normalizacion": "2022-04-21 19:00"
    },
    {
      "partido": "PILAR",
      "localidad": "PILAR",
      "subestacion_alimentador": "- / R:MANZONE / 257-TR1 / 257-5512",
      "usuarios": "3",
      "normalizacion": "2022-04-21 19:00"
    }
  ],
  "cortesComunicados": [],
  "cortesServicioBaja": [
    {
      "partido": "CAPITAL FEDERAL",
      "localidad": "PALERMO",
      "usuarios": "4"
    }
  ]
}
