{
  "fuente": "Web Service",
  "empresa": "EDENOR",
  "totalUsuariosSinSuministro": "4.928",
  "totalUsuariosConSuministro": "2.993.563",
  "ultimaActualizacion": "10:25",
  "totalUsuariosAyer": "43.466",
  "cortesPreventivos": [],
  "cortesProgramados": [
    {
      "partido": "GRAL SAN MARTIN",
      "localidad": "GRAL EUGENIO NECOCHEA",
      "subestacion_alimentador": "- / R:SUAREZ / 266-TR1 / 266-5516",
      "usuarios": "509",
      "normalizacion": "2022-03-23 12:00"
    },
    {
      "partido": "LA MATANZA",
      "localidad": "GONZALEZ CATAN",
      "subestacion_alimentador": "- / N:GONZALEZ CATAN / 168-TR2 / 168-5526",
      "usuarios": "611",
      "normalizacion": "2022-03-23 11:00"
    },
    {
      "partido": "LA MATANZA",
      "localidad": "LOMAS DEL MIRADOR",
      "subestacion_alimentador": "- / R:SAN JUSTO / 164-TR1 / 164-5511",
      "usuarios": "269",
      "normalizacion": "2022-03-23 11:00"
    },
    {
      "partido": "LA MATANZA",
      "localidad": "SAN JUSTO",
      "subestacion_alimentador": "- / R:LUZURIAGA / 64-TR2 / 64-5591 / 64-5516",
      "usuarios": "372",
      "normalizacion": "2022-03-23 12:00"
    },
    {
      "partido": "LA MATANZA",
      "localidad": "VILLA MADERO",
      "subestacion_alimentador": "- / R:TAPIALES / 162-TR2 / 162-5527",
      "usuarios": "186",
      "normalizacion": "2022-03-23 12:00"
    },
    {
      "partido": "MALVINAS ARGENTINAS",
      "localidad": "LOS POLVORINES",
      "subestacion_alimentador": "- / R:NOGUES / 159-TR2 / 159-5528",
      "usuarios": "217",
      "normalizacion": "Sin datos"
    },
    {
      "partido": "PILAR",
      "localidad": "PTE DERQUI",
      "subestacion_alimentador": "- / R:DERQUI / 260-TR1 / 260-5518",
      "usuarios": "221",
      "normalizacion": "2022-03-23 12:00"
    },
    {
      "partido": "SAN MIGUEL",
      "localidad": "BELLA VISTA",
      "subestacion_alimentador": "- / R:MORON / 67-TR4 / 67-5524",
      "usuarios": "186",
      "normalizacion": "2022-03-23 11:00"
    },
    {
      "partido": "TIGRE",
      "localidad": "DELTA 1RA SECCION (TI)",
      "subestacion_alimentador": "- / R:TIGRE / 153-TR1 / 153-5517",
      "usuarios": "11",
      "normalizacion": "2022-03-23 11:00"
    }
  ],
  "cortesServicioMedia": [
    {
      "partido": "",
      "localidad": "",
      "subestacion_alimentador": "- / R:LUZURIAGA / 64-TR2",
      "usuarios": "122",
      "normalizacion": "Sin datos"
    },
    {
      "partido": "LA MATANZA",
      "localidad": "SAN JUSTO",
      "subestacion_alimentador": "- / R:LUZURIAGA / 64-TR2",
      "usuarios": "731",
      "normalizacion": "Sin datos"
    },
    {
      "partido": "LA MATANZA",
      "localidad": "VILLA LUZURIAGA",
      "subestacion_alimentador": "- / R:LUZURIAGA / 64-TR2",
      "usuarios": "1286",
      "normalizacion": "Sin datos"
    }
  ],
  "cortesComunicados": [],
  "cortesServicioBaja": [
    {
      "partido": "CAPITAL FEDERAL",
      "localidad": "RECOLETA",
      "usuarios": "9"
    },
    {
      "partido": "CAPITAL FEDERAL",
      "localidad": "VILLA URQUIZA",
      "usuarios": "7"
    },
    {
      "partido": "ESCOBAR",
      "localidad": "MATHEU",
      "usuarios": "7"
    },
    {
      "partido": "GRAL RODRIGUEZ",
      "localidad": "GRAL RODRIGUEZ",
      "usuarios": "30"
    },
    {
      "partido": "MALVINAS ARGENTINAS",
      "localidad": "GRAND BOURG",
      "usuarios": "25"
    },
    {
      "partido": "MERLO",
      "localidad": "MERLO",
      "usuarios": "34"
    },
    {
      "partido": "MORENO",
      "localidad": "TRUJUI",
      "usuarios": "13"
    },
    {
      "partido": "MORON",
      "localidad": "CASTELAR",
      "usuarios": "6"
    },
    {
      "partido": "PILAR",
      "localidad": "VILLA ROSA",
      "usuarios": "76"
    }
  ]
}
